global_utils/__init__.py
global_utils/__main__.py
global_utils/gbutils.py
global_utils/global_utils.txt
global_utils/global_utils_functions.py
global_utils_88-0.0.7.dist-info/METADATA
global_utils_88-0.0.7.dist-info/WHEEL
global_utils_88-0.0.7.dist-info/entry_points.txt
global_utils_88-0.0.7.dist-info/top_level.txt
global_utils_88-0.0.7.dist-info/RECORD
