Metadata-Version: 2.1
Name: global-utils-88
Version: 0.0.7
Summary: gUtils. Use it everywhere!
Home-page: UNKNOWN
Author: lorepieri
License: MIT
Platform: UNKNOWN
Classifier: License :: OSI Approved :: MIT License
Classifier: Programming Language :: Python :: 3
Classifier: Programming Language :: Python :: 3.7
Requires-Dist: pybase64
Requires-Dist: datetime
